dea_dnsup/__init__.py
dea_dnsup/_version.py
dea_dnsup-0.2.1.dist-info/METADATA
dea_dnsup-0.2.1.dist-info/WHEEL
dea_dnsup-0.2.1.dist-info/entry_points.txt
dea_dnsup-0.2.1.dist-info/top_level.txt
dea_dnsup-0.2.1.dist-info/RECORD
