Metadata-Version: 2.1
Name: dea-dnsup
Version: 0.2.1
Summary: Update DNS records for EC2 instances using route53 service
Home-page: https://github.com/GeoscienceAustralia/dea-dnsup/
Author: Open Data Cube
Author-email: 
Maintainer: Open Data Cube
Maintainer-email: 
License: Apache License 2.0
Platform: any
Requires-Python: >=3.6
Requires-Dist: odc-cloud
